jeasydata/__init__.py
jeasydata/easydata.py
jeasydata-0.1.3.dist-info/METADATA
jeasydata-0.1.3.dist-info/WHEEL
jeasydata-0.1.3.dist-info/top_level.txt
jeasydata-0.1.3.dist-info/RECORD
