Metadata-Version: 2.4
Name: Jeasydata
Version: 0.1.3
Summary: Janek's easy data reader/writer
Author: janektech.pl
License: MIT
Requires-Python: >=3.8
